{"_index":"domoticz-2018-05-05","_type":"notification","_id":"Fri May 04 2018 21:33:18 GMT-0400 (EDT)","_score":1,"_source":{"message":"Plug (Wink Turned On","priority":"0","timestamp":"2018-05-05T01:33:18.499Z","host":"domoticz"}}
{"_index":"domoticz-2018-05-05","_type":"notification","_id":"Fri May 04 2018 23:26:18 GMT-0400 (EDT)","_score":1,"_source":{"message":"Smart Plug (AP) Turned On","priority":"0","timestamp":"2018-05-05T03:26:18.565Z","host":"domoticz"}}
{"_index":"domoticz-2018-05-05","_type":"notification","_id":"Sat May 05 2018 00:38:12 GMT-0400 (EDT)","_score":1,"_source":{"message":"Plug (Wink Turned On","priority":"0","timestamp":"2018-05-05T04:38:12.664Z","host":"domoticz"}}
{"_index":"domoticz-2018-05-05","_type":"notification","_id":"Sat May 05 2018 03:45:10 GMT-0400 (EDT)","_score":1,"_source":{"message":"Plug (Wink Turned Off","priority":"0","timestamp":"2018-05-05T07:45:10.857Z","host":"domoticz"}}
{"_index":"domoticz-2018-05-05","_type":"notification","_id":"Sat May 05 2018 07:48:22 GMT-0400 (EDT)","_score":1,"_source":{"message":"Plug (Wink Turned On","priority":"0","timestamp":"2018-05-05T11:48:22.516Z","host":"domoticz"}}
{"_index":"domoticz-2018-05-05","_type":"notification","_id":"Sat May 05 2018 10:55:09 GMT-0400 (EDT)","_score":1,"_source":{"message":"Plug (Wink Turned Off","priority":"0","timestamp":"2018-05-05T14:55:09.404Z","host":"domoticz"}}
{"_index":"domoticz-2018-05-05","_type":"notification","_id":"Sat May 05 2018 15:00:46 GMT-0400 (EDT)","_score":1,"_source":{"message":"Plug (Wink Turned Off","priority":"0","timestamp":"2018-05-05T19:00:46.071Z","host":"domoticz"}}
{"_index":"domoticz-2018-05-05","_type":"notification","_id":"Sat May 05 2018 19:56:19 GMT-0400 (EDT)","_score":1,"_source":{"message":"Smart Plug (AP) Turned On","priority":"0","timestamp":"2018-05-05T23:56:19.130Z","host":"domoticz"}}
{"_index":"domoticz-2018-05-05","_type":"notification","_id":"Fri May 04 2018 20:31:18 GMT-0400 (EDT)","_score":1,"_source":{"message":"Plug (Wink Turned Off","priority":"0","timestamp":"2018-05-05T00:31:18.216Z","host":"domoticz"}}
{"_index":"domoticz-2018-05-05","_type":"notification","_id":"Sat May 05 2018 05:48:11 GMT-0400 (EDT)","_score":1,"_source":{"message":"Plug (Wink Turned On","priority":"0","timestamp":"2018-05-05T09:48:11.333Z","host":"domoticz"}}
{"_index":"domoticz-2018-05-05","_type":"notification","_id":"Sat May 05 2018 07:41:20 GMT-0400 (EDT)","_score":1,"_source":{"message":"Smart Plug (AP) Turned On","priority":"0","timestamp":"2018-05-05T11:41:20.681Z","host":"domoticz"}}
{"_index":"domoticz-2018-05-05","_type":"notification","_id":"Sat May 05 2018 08:41:25 GMT-0400 (EDT)","_score":1,"_source":{"message":"Smart Plug (AP) Turned On","priority":"0","timestamp":"2018-05-05T12:41:25.751Z","host":"domoticz"}}
{"_index":"domoticz-2018-05-05","_type":"notification","_id":"Sat May 05 2018 08:50:28 GMT-0400 (EDT)","_score":1,"_source":{"message":"Plug (Wink Turned Off","priority":"0","timestamp":"2018-05-05T12:50:28.822Z","host":"domoticz"}}
{"_index":"domoticz-2018-05-05","_type":"notification","_id":"Sat May 05 2018 15:51:32 GMT-0400 (EDT)","_score":1,"_source":{"message":"Smart Plug (AP) Turned On","priority":"0","timestamp":"2018-05-05T19:51:32.536Z","host":"domoticz"}}
{"_index":"domoticz-2018-05-05","_type":"notification","_id":"Sat May 05 2018 17:40:14 GMT-0400 (EDT)","_score":1,"_source":{"message":"Lamp Turned On","priority":"0","timestamp":"2018-05-05T21:40:14.362Z","host":"domoticz"}}
{"_index":"domoticz-2018-05-05","_type":"notification","_id":"Fri May 04 2018 22:35:08 GMT-0400 (EDT)","_score":1,"_source":{"message":"Plug (Wink Turned Off","priority":"0","timestamp":"2018-05-05T02:35:08.098Z","host":"domoticz"}}
{"_index":"domoticz-2018-05-05","_type":"notification","_id":"Sat May 05 2018 06:48:22 GMT-0400 (EDT)","_score":1,"_source":{"message":"Plug (Wink Turned On","priority":"0","timestamp":"2018-05-05T10:48:22.115Z","host":"domoticz"}}
{"_index":"domoticz-2018-05-05","_type":"notification","_id":"Sat May 05 2018 07:56:00 GMT-0400 (EDT)","_score":1,"_source":{"message":"Sensor swx-u-range-sensor-light-1 Last Update: 2018-04-20 06:49:16 [!= 1 minutes]","priority":"0","timestamp":"2018-05-05T11:56:00.851Z","host":"domoticz"}}
{"_index":"domoticz-2018-05-05","_type":"notification","_id":"Sat May 05 2018 11:47:21 GMT-0400 (EDT)","_score":1,"_source":{"message":"Smart Plug (AP) Turned On","priority":"0","timestamp":"2018-05-05T15:47:21.193Z","host":"domoticz"}}
{"_index":"domoticz-2018-05-05","_type":"notification","_id":"Sat May 05 2018 14:51:12 GMT-0400 (EDT)","_score":1,"_source":{"message":"Smart Plug (AP) Turned On","priority":"0","timestamp":"2018-05-05T18:51:12.203Z","host":"domoticz"}}
{"_index":"domoticz-2018-05-05","_type":"notification","_id":"Sat May 05 2018 19:56:00 GMT-0400 (EDT)","_score":1,"_source":{"message":"Sensor swx-u-range-sensor-light-1 Last Update: 2018-04-20 06:49:16 [!= 1 minutes]","priority":"0","timestamp":"2018-05-05T23:56:00.544Z","host":"domoticz"}}
{"_index":"domoticz-2018-05-05","_type":"notification","_id":"Fri May 04 2018 20:10:37 GMT-0400 (EDT)","_score":1,"_source":{"message":"Lamp Turned On","priority":"0","timestamp":"2018-05-05T00:10:37.607Z","host":"domoticz"}}
{"_index":"domoticz-2018-05-05","_type":"notification","_id":"Sat May 05 2018 02:15:39 GMT-0400 (EDT)","_score":1,"_source":{"message":"Lamp Turned On","priority":"0","timestamp":"2018-05-05T06:15:39.812Z","host":"domoticz"}}
{"_index":"domoticz-2018-05-05","_type":"notification","_id":"Sat May 05 2018 10:46:32 GMT-0400 (EDT)","_score":1,"_source":{"message":"Smart Plug (AP) Turned On","priority":"0","timestamp":"2018-05-05T14:46:32.375Z","host":"domoticz"}}
{"_index":"domoticz-2018-05-05","_type":"notification","_id":"Sat May 05 2018 19:03:17 GMT-0400 (EDT)","_score":1,"_source":{"message":"Plug (Wink Turned On","priority":"0","timestamp":"2018-05-05T23:03:17.392Z","host":"domoticz"}}
{"_index":"domoticz-2018-05-05","_type":"notification","_id":"Sat May 05 2018 01:40:28 GMT-0400 (EDT)","_score":1,"_source":{"message":"Plug (Wink Turned Off","priority":"0","timestamp":"2018-05-05T05:40:28.665Z","host":"domoticz"}}
{"_index":"domoticz-2018-05-05","_type":"notification","_id":"Sat May 05 2018 09:46:24 GMT-0400 (EDT)","_score":1,"_source":{"message":"Smart Plug (AP) Turned On","priority":"0","timestamp":"2018-05-05T13:46:24.009Z","host":"domoticz"}}
{"_index":"domoticz-2018-05-05","_type":"notification","_id":"Sat May 05 2018 12:35:07 GMT-0400 (EDT)","_score":1,"_source":{"message":"Lamp Turned On","priority":"0","timestamp":"2018-05-05T16:35:07.850Z","host":"domoticz"}}
{"_index":"domoticz-2018-05-05","_type":"notification","_id":"Sat May 05 2018 19:40:30 GMT-0400 (EDT)","_score":1,"_source":{"message":"Lamp Turned On","priority":"0","timestamp":"2018-05-05T23:40:30.023Z","host":"domoticz"}}
